LICENSE.txt
README.md
setup.py
bin/mbank_compare_volumes
bin/mbank_compute_volume
bin/mbank_generate_flow_dataset
bin/mbank_injections
bin/mbank_injections_workflow
bin/mbank_injfile
bin/mbank_mcmc
bin/mbank_merge
bin/mbank_place_templates
bin/mbank_print_metric
bin/mbank_run
bin/mbank_train_flow
bin/mbank_validate_metric
gw_mbank.egg-info/PKG-INFO
gw_mbank.egg-info/SOURCES.txt
gw_mbank.egg-info/dependency_links.txt
gw_mbank.egg-info/requires.txt
gw_mbank.egg-info/top_level.txt
mbank/__init__.py
mbank/bank.py
mbank/handlers.py
mbank/metric.py
mbank/parser.py
mbank/placement.py
mbank/utils.py
mbank/flow/__init__.py
mbank/flow/flowmodel.py
mbank/flow/utils.py