Metadata-Version: 2.1
Name: gw-mbank
Version: 1.1.1
Summary: Metric bank generation for gravitational waves data analysis
Home-page: https://github.com/stefanoschmidt1995/mbank
Author: Stefano Schmidt
Author-email: stefanoschmidt1995@gmail.com
License: GNU GENERAL PUBLIC LICENSE v3
Platform: UNKNOWN
Classifier: Programming Language :: Python :: 3
Classifier: Operating System :: OS Independent
Requires-Python: >=3.7
License-File: LICENSE.txt
